LICENSE.md
retentioneering/__init__.py
retentioneering/__version__.py
retentioneering/backend/__init__.py
retentioneering/backend/callback/__init__.py
retentioneering/backend/callback/list_dataprocessors.py
retentioneering/backend/callback/mock_list_dataprocessor.py
retentioneering/backend/counter.py
retentioneering/backend/jupiter_server.py
retentioneering/backend/server_manager.py
retentioneering/backend/tracker/__init__.py
retentioneering/backend/tracker/connector/__init__.py
retentioneering/backend/tracker/connector/csv_connector.py
retentioneering/backend/tracker/connector/protocol.py
retentioneering/backend/tracker/connector/rete_connector.py
retentioneering/backend/tracker/tracker.py
retentioneering/backend/tracker/tracking_info.py
retentioneering/constants/__init__.py
retentioneering/constants/constants.py
retentioneering/data_processor/__init__.py
retentioneering/data_processor/data_processor.py
retentioneering/data_processor/registry.py
retentioneering/data_processors_lib/__init__.py
retentioneering/data_processors_lib/add_negative_events.py
retentioneering/data_processors_lib/add_positive_events.py
retentioneering/data_processors_lib/add_start_end_events.py
retentioneering/data_processors_lib/collapse_loops.py
retentioneering/data_processors_lib/drop_paths.py
retentioneering/data_processors_lib/filter_events.py
retentioneering/data_processors_lib/group_events.py
retentioneering/data_processors_lib/group_events_bulk.py
retentioneering/data_processors_lib/label_cropped_paths.py
retentioneering/data_processors_lib/label_lost_users.py
retentioneering/data_processors_lib/label_new_users.py
retentioneering/data_processors_lib/pipe.py
retentioneering/data_processors_lib/rename.py
retentioneering/data_processors_lib/split_sessions.py
retentioneering/data_processors_lib/truncate_paths.py
retentioneering/datasets/__init__.py
retentioneering/datasets/data/__init__.py
retentioneering/datasets/data/ab_test_demo.csv
retentioneering/datasets/data/simple-onlineshop.csv
retentioneering-3.3.0.dist-info/LICENSE.md
retentioneering-3.3.0.dist-info/WHEEL
retentioneering-3.3.0.dist-info/METADATA
retentioneering-3.3.0.dist-info/RECORD
