Metadata-Version: 2.1
Name: retentioneering
Version: 3.3.0
Summary: Retentioneering is a Python library that makes analyzing clickstreams, user paths (trajectories), and event logs much easier, and yields much broader and deeper insights than funnel analysis. You can use Retentioneering to explore user behavior, segment users, and form hypotheses about what drives users to desirable actions or to churning away from a product.
License: Retentioneering Software Non-Exclusive License
Author: Retentioneering User Trajectory Analysis Lab
Author-email: retentioneering@gmail.com
Requires-Python: >=3.8,<3.12
Classifier: License :: Other/Proprietary License
Classifier: Operating System :: MacOS
Classifier: Operating System :: Microsoft :: Windows
Classifier: Operating System :: Unix
Classifier: Programming Language :: Python :: 3
Classifier: Programming Language :: Python :: 3.8
Classifier: Programming Language :: Python :: 3.9
Classifier: Programming Language :: Python :: 3.10
Classifier: Programming Language :: Python :: 3.11
Classifier: Programming Language :: Python :: 3
Requires-Dist: docrep (>=0.3.2,<0.4.0)
Requires-Dist: ipykernel (==5.5.6)
Requires-Dist: ipython (==7.34.0)
Requires-Dist: ipywidgets (>=8.0.4,!=8.0.5)
Requires-Dist: jupyterlab (>=3.4.7)
Requires-Dist: matplotlib (==3.7.2)
Requires-Dist: nanoid (>=2.0.0,<3.0.0)
Requires-Dist: networkx (==2.8.6)
Requires-Dist: notebook (>=6.5.6)
Requires-Dist: numpy (>=1.22,!=1.24)
Requires-Dist: pandas (>=1.5.0,<2.0.0)
Requires-Dist: plotly (>=5.10.0)
Requires-Dist: pydantic (>=1.10.2,<2)
Requires-Dist: pyzmq (==23.2.1)
Requires-Dist: scikit-learn (>=1.2.0,<1.3.0)
Requires-Dist: scipy (==1.10.1); python_version < "3.9"
Requires-Dist: scipy (>=1.11.2); python_version >= "3.9"
Requires-Dist: seaborn (>=0.12.1)
Requires-Dist: statsmodels (>=0.14.0)
Requires-Dist: tornado (==6.3.2)
Requires-Dist: umap-learn (>=0.5.3)
Requires-Dist: virtualenv (>=20.17)
